icezip.py
icezip-1.0.2.dist-info/licenses/LICENSE
icezip-1.0.2.dist-info/METADATA
icezip-1.0.2.dist-info/WHEEL
icezip-1.0.2.dist-info/entry_points.txt
icezip-1.0.2.dist-info/top_level.txt
icezip-1.0.2.dist-info/RECORD
