Metadata-Version: 2.4
Name: icezip
Version: 1.0.2
Summary: Advanced lightweight ICEZIP archive tool
Home-page: https://github.com/Icelandmc/Ice-zip
Author: Iceland
Author-email: icelandmc.help@gmail.com
Classifier: Programming Language :: Python :: 3
Classifier: License :: OSI Approved :: MIT License
Classifier: Operating System :: OS Independent
Requires-Python: >=3.7
License-File: LICENSE
Dynamic: author
Dynamic: author-email
Dynamic: classifier
Dynamic: home-page
Dynamic: license-file
Dynamic: requires-python
Dynamic: summary
